helloworld.py
hello_sahaj_raj_malla-0.0.1.dist-info/LICENSE
hello_sahaj_raj_malla-0.0.1.dist-info/METADATA
hello_sahaj_raj_malla-0.0.1.dist-info/WHEEL
hello_sahaj_raj_malla-0.0.1.dist-info/top_level.txt
hello_sahaj_raj_malla-0.0.1.dist-info/RECORD
